gwws/__init__.py
gwws/gimy_scrape.py
gwws/scrape.py
gwws_genwch-0.0.10.dist-info/LICENSE
gwws_genwch-0.0.10.dist-info/METADATA
gwws_genwch-0.0.10.dist-info/WHEEL
gwws_genwch-0.0.10.dist-info/top_level.txt
gwws_genwch-0.0.10.dist-info/RECORD
